aidbox_python_sdk_tbs/__init__.py
aidbox_python_sdk_tbs/implementation.py
aidbox_python_sdk_tbs/py.typed
aidbox_python_sdk_tbs/r4b.py
aidbox_python_sdk_tbs/r5.py
aidbox_python_sdk_tbs/types.py
aidbox_python_sdk_tbs-0.0.1a5.dist-info/LICENSE.md
aidbox_python_sdk_tbs-0.0.1a5.dist-info/WHEEL
aidbox_python_sdk_tbs-0.0.1a5.dist-info/METADATA
aidbox_python_sdk_tbs-0.0.1a5.dist-info/RECORD
